mysql_vector/__init__.py
mysql_vector/cli.py
mysql_vector-0.0.0.dist-info/LICENSE
mysql_vector-0.0.0.dist-info/METADATA
mysql_vector-0.0.0.dist-info/WHEEL
mysql_vector-0.0.0.dist-info/entry_points.txt
mysql_vector-0.0.0.dist-info/top_level.txt
mysql_vector-0.0.0.dist-info/RECORD
