Metadata-Version: 2.1
Name: mysql_vector
Version: 0.0.0
Summary: Use MySQL as a vector Database
Home-page: https://github.com/Adwaith-Rajesh/mysql-vector
Author: Adwaith Rajesh
Author-email: adwaithrajesh3180@gmail.com
License: MIT
Classifier: Intended Audience :: Developers
Classifier: License :: OSI Approved :: MIT License
Classifier: Programming Language :: Python
Classifier: Programming Language :: Python :: 3
Classifier: Programming Language :: Python :: 3 :: Only
Requires-Python: >=3.12
License-File: LICENSE
Requires-Dist: aiomysql>=0.2.0
Requires-Dist: numpy>=2.1.3
Requires-Dist: scipy>=1.14.1
